{"moduleDefinition":{"range":[1,1,1,37],"value":{"type":"normal","normal":{"moduleName":{"range":[1,8,1,23],"value":["Helpers","Vector2"]},"exposingList":{"range":[1,24,1,37],"value":{"type":"all","all":[1,34,1,36]}}}}},"imports":[],"declarations":[{"range":[3,1,5,17],"value":{"type":"typeAlias","typeAlias":{"documentation":null,"name":{"range":[3,12,3,19],"value":"Vector2"},"generics":[],"typeAnnotation":{"range":[4,5,5,17],"value":{"type":"record","record":{"value":[{"range":[4,7,4,16],"value":{"name":{"range":[4,7,4,8],"value":"x"},"typeAnnotation":{"range":[4,11,4,16],"value":{"type":"typed","typed":{"moduleNameAndName":{"range":[4,11,4,16],"value":{"moduleName":[],"name":"Float"}},"args":[]}}}}},{"range":[5,5,5,16],"value":{"name":{"range":[5,7,5,8],"value":"y"},"typeAnnotation":{"range":[5,11,5,16],"value":{"type":"typed","typed":{"moduleNameAndName":{"range":[5,11,5,16],"value":{"moduleName":[],"name":"Float"}},"args":[]}}}}}]}}}}}},{"range":[8,1,10,16],"value":{"type":"function","function":{"documentation":null,"signature":{"range":[8,1,8,42],"value":{"name":{"range":[8,1,8,13],"value":"isPointAbove"},"typeAnnotation":{"range":[8,16,8,42],"value":{"type":"function","function":{"left":{"range":[8,16,8,23],"value":{"type":"typed","typed":{"moduleNameAndName":{"range":[8,16,8,23],"value":{"moduleName":[],"name":"Vector2"}},"args":[]}}},"right":{"range":[8,27,8,42],"value":{"type":"function","function":{"left":{"range":[8,27,8,34],"value":{"type":"typed","typed":{"moduleNameAndName":{"range":[8,27,8,34],"value":{"moduleName":[],"name":"Vector2"}},"args":[]}}},"right":{"range":[8,38,8,42],"value":{"type":"typed","typed":{"moduleNameAndName":{"range":[8,38,8,42],"value":{"moduleName":[],"name":"Bool"}},"args":[]}}}}}}}}}}},"declaration":{"range":[9,1,10,16],"value":{"name":{"range":[9,1,9,13],"value":"isPointAbove"},"arguments":[{"range":[9,14,9,16],"value":{"type":"var","var":{"value":"v1"}}},{"range":[9,17,9,19],"value":{"type":"var","var":{"value":"v2"}}}],"expression":{"range":[10,7,10,16],"value":{"type":"application","application":[{"range":[10,7,10,9],"value":{"type":"recordAccess","recordAccess":{"expression":{"range":[10,5,10,7],"value":{"type":"functionOrValue","functionOrValue":{"moduleName":[],"name":"v1"}}},"name":{"range":[10,8,10,9],"value":"y"}}}},{"range":[10,10,10,11],"value":{"type":"operator","operator":"<"}},{"range":[10,14,10,16],"value":{"type":"recordAccess","recordAccess":{"expression":{"range":[10,12,10,14],"value":{"type":"functionOrValue","functionOrValue":{"moduleName":[],"name":"v2"}}},"name":{"range":[10,15,10,16],"value":"y"}}}}]}}}}}}}],"comments":[{"range":[11,5,11,78],"value":"-- it's backwards because the y-axis increases from top to bottom in HTML"}]}